pyeventbt/__init__.py
pyeventbt/app.py
pyeventbt/backtest/__init__.py
pyeventbt/backtest/core/__init__.py
pyeventbt/backtest/core/backtest_results.py
pyeventbt/broker/__init__.py
pyeventbt/broker/mt5_broker/__init__.py
pyeventbt/broker/mt5_broker/connectors/__init__.py
pyeventbt/broker/mt5_broker/connectors/live_mt5_broker.py
pyeventbt/broker/mt5_broker/connectors/mt5_simulator_connector.py
pyeventbt/broker/mt5_broker/core/__init__.py
pyeventbt/broker/mt5_broker/core/entities/__init__.py
pyeventbt/broker/mt5_broker/core/entities/account_info.py
pyeventbt/broker/mt5_broker/core/entities/init_credentials.py
pyeventbt/broker/mt5_broker/core/entities/mt5_closed_position.py
pyeventbt/broker/mt5_broker/core/entities/order_send_result.py
pyeventbt/broker/mt5_broker/core/entities/symbol_info.py
pyeventbt/broker/mt5_broker/core/entities/terminal_info.py
pyeventbt/broker/mt5_broker/core/entities/tick.py
pyeventbt/broker/mt5_broker/core/entities/trade_deal.py
pyeventbt/broker/mt5_broker/core/entities/trade_order.py
pyeventbt/broker/mt5_broker/core/entities/trade_position.py
pyeventbt/broker/mt5_broker/core/entities/trade_request.py
pyeventbt/broker/mt5_broker/core/interfaces/__init__.py
pyeventbt/broker/mt5_broker/core/interfaces/mt5_broker_interface.py
pyeventbt/broker/mt5_broker/mt5_simulator_wrapper.py
pyeventbt/broker/mt5_broker/shared/__init__.py
pyeventbt/broker/mt5_broker/shared/default_account_info.yaml
pyeventbt/broker/mt5_broker/shared/default_symbols_info.yaml
pyeventbt/broker/mt5_broker/shared/default_terminal_info.yaml
pyeventbt/broker/mt5_broker/shared/shared_data.py
pyeventbt/config/__init__.py
pyeventbt/config/configs.py
pyeventbt/config/core/__init__.py
pyeventbt/config/core/entities/__init__.py
pyeventbt/config/core/entities/base_config.py
pyeventbt/core/__init__.py
pyeventbt/core/entities/__init__.py
pyeventbt/core/entities/hyper_parameter.py
pyeventbt/core/entities/variable.py
pyeventbt/data_provider/__init__.py
pyeventbt-0.0.4.dist-info/METADATA
pyeventbt-0.0.4.dist-info/WHEEL
pyeventbt-0.0.4.dist-info/entry_points.txt
pyeventbt-0.0.4.dist-info/licenses/LICENSE
pyeventbt-0.0.4.dist-info/RECORD
