Metadata-Version: 2.4
Name: pyeventbt
Version: 0.0.4
Summary: Event-driven backtesting and live trading framework for Python and MetaTrader 5
License: Apache-2.0
License-File: LICENSE
Keywords: mt5,metatrader5,backtesting,mt5 python,event-driven,trading
Author: Marti Castany, Alain Porto
Requires-Python: >=3.12,<4.0
Classifier: Development Status :: 1 - Planning
Classifier: Intended Audience :: Developers
Classifier: License :: OSI Approved :: Apache Software License
Classifier: Programming Language :: Python :: 3
Classifier: Programming Language :: Python :: 3.12
Classifier: Programming Language :: Python :: 3.13
Classifier: Programming Language :: Python :: 3.14
Requires-Dist: PyYAML (>=6.0,<7.0)
Requires-Dist: matplotlib (>=3.7.0,<4.0.0)
Requires-Dist: numba (>=0.62.1,<0.63.0)
Requires-Dist: numpy (>=2.0.0,<3.0.0)
Requires-Dist: pandas (>=2.2.3,<3.0.0)
Requires-Dist: polars (>=1.35.0,<2.0.0)
Requires-Dist: pydantic (>=2.12.3,<3.0.0)
Requires-Dist: python-dotenv (>=1.1.1,<2.0.0)
Requires-Dist: scikit-learn (>=1.3.0,<2.0.0)
Requires-Dist: scipy (>=1.10.0,<2.0.0)
Project-URL: Homepage, https://github.com/marticastany/pyeventbt
Project-URL: Repository, https://github.com/marticastany/pyeventbt
